terminate_thread/__init__.py
terminate_thread/libterminate.dll
terminate_thread/libterminate.so
terminate_thread/terminate_thread.py
terminate_thread-0.0.4.dist-info/METADATA
terminate_thread-0.0.4.dist-info/WHEEL
terminate_thread-0.0.4.dist-info/top_level.txt
terminate_thread-0.0.4.dist-info/RECORD
