Metadata-Version: 2.4
Name: terminate_thread
Version: 0.0.4
Summary: terminate_thread
Author-email: calm51 <calm51@protonmail.com>
Project-URL: Homepage, https://github.com/calm51/terminate_thread
Project-URL: Issues, https://github.com/calm51/terminate_thread/issues
Keywords: terminate thread,kill thread,stop thread
Classifier: Programming Language :: Python :: 3
Requires-Python: >=3.6
